setup.py
t411api/API.py
t411api/__init__.py
t411api/helpers.py
t411api/version.py
t411api.egg-info/PKG-INFO
t411api.egg-info/SOURCES.txt
t411api.egg-info/dependency_links.txt
t411api.egg-info/not-zip-safe
t411api.egg-info/requires.txt
t411api.egg-info/top_level.txt