Metadata-Version: 1.1
Name: t411api
Version: 0.1.3
Summary: Lightweight API for T411 (french torrent website)
Home-page: https://github.com/Xide/t411api
Author: Germain Gau
Author-email: germain.gau@gmail.com
License: THE BEER-WARE LICENSE
Platform: UNKNOWN
Classifier: Development Status :: 4 - Beta
Classifier: Intended Audience :: Developers
Classifier: Programming Language :: Python :: 3
Classifier: Programming Language :: Python :: 3.5
Classifier: Topic :: Software Development :: Libraries :: Python Modules
Classifier: Programming Language :: Python
Classifier: Operating System :: Unix
